pymol_remote/__init__.py
pymol_remote/client.py
pymol_remote/common.py
pymol_remote/server.py
pymol_remote/style.py
pymol_remote/version.py
pymol_remote-1.0.0.dist-info/METADATA
pymol_remote-1.0.0.dist-info/WHEEL
pymol_remote-1.0.0.dist-info/entry_points.txt
pymol_remote-1.0.0.dist-info/licenses/LICENSE
pymol_remote-1.0.0.dist-info/RECORD
