Metadata-Version: 2.4
Name: pymol_remote
Version: 1.0.0
Project-URL: Homepage, https://github.com/Croydon-Brixton/pymol-remote
Author-email: Simon Mathis <simon.mathis@gmail.com>
License: // Last Update: 2024-07-23
License-File: LICENSE
Requires-Python: >=3.8
